OptimoTests/__init__.py
Optimo_Instance_Manager/__init__.py
Optimo_Instance_Manager/manager.py
Optimo_API_Testing-2.0.0.dist-info/METADATA
Optimo_API_Testing-2.0.0.dist-info/WHEEL
Optimo_API_Testing-2.0.0.dist-info/top_level.txt
Optimo_API_Testing-2.0.0.dist-info/RECORD
