Metadata-Version: 2.1
Name: Optimo-API-Testing
Version: 2.0.0
Summary: Package for testing optimo API
Home-page: UNKNOWN
Author: Bacho Labadze
Author-email: bachukilabadze@gmail.com
License: UNKNOWN
Platform: UNKNOWN
Requires-Dist: allure-behave (==2.13.1)
Requires-Dist: allure-python-commons (==2.13.1)
Requires-Dist: async-generator (==1.10)
Requires-Dist: attrs (==22.2.0)
Requires-Dist: awscli (==1.27.159)
Requires-Dist: behave (==1.2.6)
Requires-Dist: bleach (==6.0.0)
Requires-Dist: boto3 (==1.26.159)
Requires-Dist: botocore (==1.29.159)
Requires-Dist: certifi (==2022.12.7)
Requires-Dist: cffi (==1.15.1)
Requires-Dist: charset-normalizer (==3.1.0)
Requires-Dist: colorama (==0.4.4)
Requires-Dist: cryptography (==41.0.1)
Requires-Dist: docutils (==0.16)
Requires-Dist: exceptiongroup (==1.1.0)
Requires-Dist: h11 (==0.14.0)
Requires-Dist: idna (==3.4)
Requires-Dist: importlib-metadata (==6.7.0)
Requires-Dist: iniconfig (==2.0.0)
Requires-Dist: jaraco.classes (==3.2.3)
Requires-Dist: jeepney (==0.8.0)
Requires-Dist: jmespath (==1.0.1)
Requires-Dist: keyring (==24.0.1)
Requires-Dist: Mako (==1.2.4)
Requires-Dist: markdown-it-py (==3.0.0)
Requires-Dist: MarkupSafe (==2.1.2)
Requires-Dist: mdurl (==0.1.2)
Requires-Dist: more-itertools (==9.1.0)
Requires-Dist: outcome (==1.2.0)
Requires-Dist: packaging (==23.0)
Requires-Dist: parse (==1.19.0)
Requires-Dist: parse-type (==0.6.0)
Requires-Dist: pkginfo (==1.9.6)
Requires-Dist: pluggy (==1.0.0)
Requires-Dist: pyasn1 (==0.5.0)
Requires-Dist: pycparser (==2.21)
Requires-Dist: Pygments (==2.15.1)
Requires-Dist: PySocks (==1.7.1)
Requires-Dist: pytest (==7.2.1)
Requires-Dist: pytest-asyncio (==0.21.0)
Requires-Dist: pytest-bdd (==6.1.1)
Requires-Dist: python-dateutil (==2.8.2)
Requires-Dist: PyYAML (==5.4.1)
Requires-Dist: readme-renderer (==40.0)
Requires-Dist: requests (==2.31.0)
Requires-Dist: requests-toolbelt (==1.0.0)
Requires-Dist: rfc3986 (==2.0.0)
Requires-Dist: rich (==13.4.2)
Requires-Dist: rsa (==4.7.2)
Requires-Dist: s3transfer (==0.6.1)
Requires-Dist: SecretStorage (==3.3.3)
Requires-Dist: selenium (==4.8.0)
Requires-Dist: six (==1.16.0)
Requires-Dist: sniffio (==1.3.0)
Requires-Dist: sortedcontainers (==2.4.0)
Requires-Dist: tomli (==2.0.1)
Requires-Dist: trio (==0.22.0)
Requires-Dist: trio-websocket (==0.9.2)
Requires-Dist: twine (==4.0.2)
Requires-Dist: typing-extensions (==4.4.0)
Requires-Dist: urllib3 (==1.26.14)
Requires-Dist: webencodings (==0.5.1)
Requires-Dist: wsproto (==1.2.0)
Requires-Dist: zipp (==3.15.0)
